Workbook

Sheet Use Case Catalog
B2: Dubai Police 2040 — Agentic AI Use Case Catalog (300 Use Cases)
B4: ID | C4: Mission Domain | D4: Use Case | E4: What the Agent Does | F4: How the Agent Works (Step-by-Step) | G4: Agent Pattern | H4: Audience | I4: Impact | J4: Prototype Feasibility | K4: Existence Status | L4: What Already Exists in Dubai Today | M4: Championship Category | N4: Rating (/10)
B5: D01-01 | C5: Emergency Communications & Dispatch (999/901) | D5: Multilingual 999 triage agent | E5: Detects caller language, classifies urgency, pre-briefs dispatcher before human pick-up | F5: 1) Trigger: 999 call lands; agent listens on the line from second zero 2) Perceive: detects language and emotion, classifies urgency against protocols 3) Act: builds an incident card (location, type, risk) for the dispatcher 4) Outcome: human answers already briefed - seconds saved on every call | G5: Triager | H5: External | I5: High | J5: Medium | K5: Partial | L5: 999 is human-operated with CAD in place; no AI language-detection or pre-brief triage layer runs in production. | M5: Societal | N5: 8.5
B6: D01-02 | C6: Emergency Communications & Dispatch (999/901) | D6: Silent SOS chat agent | E6: Chat-based emergency reporting for hostage or domestic-violence situations where voice is unsafe | F6: 1) Trigger: user taps Silent SOS in app or chat when speaking is unsafe 2) Perceive: pulls GPS, contact context and risk keywords; scores threat level 3) Act: streams chat to a 999 room, alerts nearest units without device sound 4) Outcome: officer joins as silent chat partner; agent relays live updates | G6: Triager | H6: External | I6: High | J6: Easy | K6: White Space | L6: Nearest today: eCrime portal and app chat - form-based only; no live, risk-adaptive silent-SOS agent. | M6: Societal | N6: 9.5
B7: D01-03 | C7: Emergency Communications & Dispatch (999/901) | D7: Sign-language & text-999 agent | E7: Emergency access for deaf and hard-of-hearing residents with live relay support | F7: 1) Trigger: deaf/hard-of-hearing user opens text-999 channel 2) Perceive: agent reads typed or relayed sign-to-text input, classifies emergency 3) Act: creates CAD incident, keeps two-way transcript flowing with dispatcher 4) Outcome: full emergency service without voice; transcript archived as record | G7: Triager | H7: External | I7: High | J7: Easy | K7: White Space | L7: No text-999 or sign-language emergency channel; accessibility limited to SPS video relay and Braille cards. | M7: Societal | N7: 8.5
B8: D01-04 | C8: Emergency Communications & Dispatch (999/901) | D8: Caller-location & nearest-unit agent | E8: Fuses GPS, camera zones and unit positions to recommend the fastest responder | F8: 1) Trigger: emergency call or sensor alert enters the dispatch queue 2) Perceive: fuses caller GPS, camera zones, traffic and unit positions 3) Act: ranks units by true arrival time, proposes dispatch set with ETAs 4) Outcome: dispatcher accepts with one tap; unit screens show the same picture | G8: Analyzer | H8: Internal | I8: High | J8: Medium | K8: Partial | L8: CAD and Oyoon hold unit and camera positions; fusing them into a fastest-responder recommendation is operator work. | M8: Business | N8: 8
B9: D01-05 | C9: Emergency Communications & Dispatch (999/901) | D9: Call-surge orchestrator | E9: Spawns triage sub-agents when call volume spikes during major city incidents | F9: 1) Trigger: call volume crosses surge threshold (major incident detected) 2) Perceive: agent groups calls by incident and priority in real time 3) Act: spawns triage sub-agents per cluster, routes overflow to them 4) Outcome: no caller abandoned; humans stay on highest-value conversations | G9: Multi-agent Swarm | H9: Internal | I9: High | J9: Medium | K9: White Space | L9: Overflow handled by static rosters; no agent that spawns triage sub-agents when call volume spikes. | M9: Business | N9: 7.5
B10: D01-06 | C10: Emergency Communications & Dispatch (999/901) | D10: Post-incident follow-up agent | E10: Contacts victims after 48 hours, checks welfare and logs satisfaction | F10: 1) Trigger: 48 hours after a reported incident closes 2) Perceive: agent reviews case status and victim contact preferences 3) Act: sends caring check-in message, offers support referrals, books callbacks 4) Outcome: welfare gaps caught early; satisfaction and trust measured | G10: Triager | H10: External | I10: High | J10: Easy | K10: White Space | L10: Victim follow-up is ad hoc; no systematic 48-hour welfare contact or case-linked satisfaction logging. | M10: Societal | N10: 9
B11: D01-07 | C11: Emergency Communications & Dispatch (999/901) | D11: Hoax-call pattern agent | E11: Scores repeat false callers and routes them to proactive intervention | F11: 1) Trigger: call-taker flags suspected hoax or repeated nuisance caller 2) Perceive: agent matches voiceprint/number history across call records 3) Act: scores hoax probability, drafts guidance note for operators 4) Outcome: repeat offenders routed to intervention, real emergencies stay clear | G11: Analyzer | H11: Internal | I11: Medium | J11: Easy | K11: Partial | L11: Hoax callers are noted in CAD records; no repeat-caller scoring or proactive intervention routing. | M11: Business | N11: 7
B12: D01-08 | C12: Emergency Communications & Dispatch (999/901) | D12: Live call-transcription agent | E12: Transcribes and tags emergency calls into CAD as searchable evidence | F12: 1) Trigger: live 999/901 call in progress 2) Perceive: agent transcribes audio, detects entities, locations, weapons, injuries 3) Act: tags and pushes structured notes into the CAD record as they occur 4) Outcome: searchable, accurate call record ready for investigators same day | G12: Analyzer | H12: Internal | I12: High | J12: Medium | K12: Partial | L12: Calls are recorded for QA; automatic transcription and tagging into searchable CAD evidence is missing. | M12: Business | N12: 8
B13: D01-09 | C13: Emergency Communications & Dispatch (999/901) | D13: Missing-person first-hours agent | E13: Runs the amber protocol: broadcasts, CCTV tasking, hospital and shelter checks | F13: 1) Trigger: missing-person report accepted by control room 2) Perceive: builds subject profile - photo, last location, habits, contacts 3) Act: runs amber protocol: broadcasts, CCTV tasking, hospital and shelter sweeps 4) Outcome: coordinated first-6-hours search; every lead logged and tracked | G13: Multi-agent Swarm | H13: Internal | I13: High | J13: Medium | K13: Partial | L13: Media appeals and manual CCTV review; the amber protocol is not automated end-to-end. | M13: Societal | N13: 9
B14: D01-10 | C14: Emergency Communications & Dispatch (999/901) | D14: Bystander first-aid coach agent | E14: Guides 999 callers through CPR and bleeding control with live video checks | F14: 1) Trigger: 999 caller is with an unconscious or bleeding person 2) Perceive: agent confirms situation type through quick voice questions 3) Act: delivers step-by-step CPR/bleeding-control instructions, times compressions 4) Outcome: bystander becomes first responder before paramedics arrive | G14: Copilot | H14: External | I14: High | J14: Medium | K14: Partial | L14: 999 operators give verbal CPR and bleeding-control instructions; no video-checked AI first-aid coach. | M14: Societal | N14: 8.5
B15: D01-11 | C15: Emergency Communications & Dispatch (999/901) | D15: Tourist SOS agent | E15: WhatsApp-native triage in 10+ languages, links embassy and hotel instantly | F15: 1) Trigger: tourist messages SOS line on WhatsApp 2) Perceive: detects language, location and emergency type automatically 3) Act: triages, connects to tourist police, alerts embassy and hotel if needed 4) Outcome: visitor handled in their own language within one conversation | G15: Triager | H15: External | I15: High | J15: Easy | K15: Partial | L15: Tourist Police units and multilingual staff exist; no WhatsApp-native SOS with instant embassy and hotel linking. | M15: Societal | N15: 9
B16: D01-12 | C16: Emergency Communications & Dispatch (999/901) | D16: Air-ambulance request agent | E16: Criteria-based HEMS dispatch with landing-zone coordination | F16: 1) Trigger: ground unit or call-taker requests air ambulance 2) Perceive: agent checks medical criteria, weather, airspace and LZ options 3) Act: packages request to HEMS with landing-zone plan and hazards 4) Outcome: criteria-based dispatch decision in minutes, fully documented | G16: Orchestrator | H16: Internal | I16: Medium | J16: Hard | K16: Partial | L16: Air ambulance is dispatched through command; criteria-based auto-dispatch and landing-zone coordination are manual. | M16: Business | N16: 7
... B304: D15-20 | C304: Intelligence, Prediction & Command (2040) | D304: Model-governance agent | E304: Monitors all police AI models for drift and bias | F304: 1) Trigger: continuous model monitoring 2) Perceive: agent tracks drift, bias and performance of all police AI 3) Act: alerts owners, drafts remediation plans 4) Outcome: the AI policing the AI - always | G304: Analyzer | H304: Internal | I304: High | J304: Medium | K304: White Space | L304: No drift and bias monitoring across police AI models. | M304: Business | N304: 8.5
B306: Source: reconstruction mapped to Dubai Police services and its announced 2040 AI opportunities, aligned with the DCAI Agentic AI for Government Services Accelerator (33 entities, 300+ public-facing use cases, Oct 2026). 'How the Agent Works' shows the trigger-perceive-act-outcome loop. Ratings /10 weigh community impact, prototype feasibility, demo-ability and governance risk. Existence Status tags what Dubai already runs: White Space = nothing comparable in production; Partial = the data/service base exists but the last mile is manual (your agentic upgrade); Exists = already solved end-to-end, avoid pitching as new.

Sheet Top 10 Picks
B2: Top 10 Championship Picks (External-Facing, Demo-Ready)
B4: Rank | C4: Ref ID | D4: Use Case | E4: Mission Domain | F4: Category | G4: Prototype Feasibility | H4: Existence Status | I4: Rating (/10) | J4: Why It Wins
B5: 1 | C5: D01-02 | D5: Silent SOS chat agent | E5: Emergency Communications & Dispatch (999/901) | F5: Societal | G5: Easy | H5: White Space | I5: 9.5 | J5: Life-saving and discreet; a 3-minute demo judges never forget. Strong Societal story.
B6: 2 | C6: D01-09 | D6: Missing-person first-hours agent | E6: Emergency Communications & Dispatch (999/901) | F6: Societal | G6: Medium | H6: Partial | I6: 9 | J6: Orchestrates the amber protocol end-to-end; high-drama live demo with clear public value.
B7: 3 | C7: D04-01 | D7: Fine-dispute assistant | E7: Traffic & Road Safety | F7: Personal | G7: Easy | H7: Partial | I7: 9.5 | J7: Everyone has fines — instant 'aha'. Measurable AED saved per user; Personal-category star.
B8: 4 | C8: D06-13 | D8: New-resident welcome agent | E8: Community Services & Smart Reports | F8: Societal | G8: Easy | H8: White Space | I8: 8.5 | J8: The Ahlan flagship: arrival-triggered onboarding no government offers yet; pure white space with daily touchpoints.
B9: 5 | C9: D07-01 | D9: Tourist guardian agent | E9: Tourist Policing | F9: Societal | G9: Easy | H9: Partial | I9: 9 | J9: Serves 17M+ visitors; multilingual wow factor, perfectly on Dubai's strategy.
B10: 6 | C10: D05-01 | D10: Scam-report triage agent | E10: Cybercrime & Digital Fraud | F10: Societal | G10: Easy | H10: Partial | I10: 9 | J10: Fraud is the city's top concern; live block-and-warn demo lands immediately.
B11: 7 | C11: D05-04 | D11: Sextortion first-responder | E11: Cybercrime & Digital Fraud | F11: Societal | G11: Easy | H11: White Space | I11: 9 | J11: Emotionally powerful, discreet chat demo; strong fit for Societal or Youth track.
B12: 8 | C12: D05-17 | D12: Elder-fraud guardian | E12: Cybercrime & Digital Fraud | F12: Societal | G12: Medium | H12: White Space | I12: 9 | J12: Pure 'anticipatory government' narrative — the agent acts before the loss happens.
B13: 9 | C13: D11-10 | D13: Cyberbullying responder | E13: Family, Women & Children Protection | F13: Youth | G13: Easy | H13: Partial | I13: 9 | J13: Best Youth-category entry; school partnerships make a real pilot achievable in weeks.
B14: 10 | C14: D06-07 | D14: Welfare-check agent | E14: Community Services & Smart Reports | F14: Societal | G14: Easy | H14: Partial | I14: 9 | J14: Anticipatory plus human warmth; ends your demo on a story judges remember.
B16: Selection lens: external-facing, high community impact, prototype-able in weeks, and aligned with the Championship judging criteria (real challenge, tested impact, scalable venture).

Sheet Domain Summary
B2: Domain Summary — Live Counts from Catalog
B4: Mission Domain | C4: Total | D4: External | E4: Internal | F4: High Impact | G4: Easy Prototype | H4: White Space | I4: Avg Rating (/10)
B5: Emergency Communications & Dispatch (999/901) | C5: =COUNTIF('Use Case Catalog'!$C$5:$C$304,$B5) -> 20 | D5: =COUNTIFS('Use Case Catalog'!$C$5:$C$304,$B5,'Use Case Catalog'!$H$5:$H$304,"External") -> 9 | E5: =COUNTIFS('Use Case Catalog'!$C$5:$C$304,$B5,'Use Case Catalog'!$H$5:$H$304,"Internal") -> 11 | F5: =COUNTIFS('Use Case Catalog'!$C$5:$C$304,$B5,'Use Case Catalog'!$I$5:$I$304,"High") -> 14 | G5: =COUNTIFS('Use Case Catalog'!$C$5:$C$304,$B5,'Use Case Catalog'!$J$5:$J$304,"Easy") -> 8 | H5: =COUNTIFS('Use Case Catalog'!$C$5:$C$304,$B5,'Use Case Catalog'!$K$5:$K$304,"White Space") -> 8 | I5: =ROUND(AVERAGEIF('Use Case Catalog'!$C$5:$C$304,$B5,'Use Case Catalog'!$N$5:$N$304),1) -> 8.2
B6: Patrol, Robots & Drones | C6: =COUNTIF('Use Case Catalog'!$C$5:$C$304,$B6) -> 20 | D6: =COUNTIFS('Use Case Catalog'!$C$5:$C$304,$B6,'Use Case Catalog'!$H$5:$H$304,"External") -> 8 | E6: =COUNTIFS('Use Case Catalog'!$C$5:$C$304,$B6,'Use Case Catalog'!$H$5:$H$304,"Internal") -> 12 | F6: =COUNTIFS('Use Case Catalog'!$C$5:$C$304,$B6,'Use Case Catalog'!$I$5:$I$304,"High") -> 11 | G6: =COUNTIFS('Use Case Catalog'!$C$5:$C$304,$B6,'Use Case Catalog'!$J$5:$J$304,"Easy") -> 5 | H6: =COUNTIFS('Use Case Catalog'!$C$5:$C$304,$B6,'Use Case Catalog'!$K$5:$K$304,"White Space") -> 4 | I6: =ROUND(AVERAGEIF('Use Case Catalog'!$C$5:$C$304,$B6,'Use Case Catalog'!$N$5:$N$304),1) -> 7.9
B7: Criminal Investigations & Forensics | C7: =COUNTIF('Use Case Catalog'!$C$5:$C$304,$B7) -> 20 | D7: =COUNTIFS('Use Case Catalog'!$C$5:$C$304,$B7,'Use Case Catalog'!$H$5:$H$304,"External") -> 1 | E7: =COUNTIFS('Use Case Catalog'!$C$5:$C$304,$B7,'Use Case Catalog'!$H$5:$H$304,"Internal") -> 19 | F7: =COUNTIFS('Use Case Catalog'!$C$5:$C$304,$B7,'Use Case Catalog'!$I$5:$I$304,"High") -> 10 | G7: =COUNTIFS('Use Case Catalog'!$C$5:$C$304,$B7,'Use Case Catalog'!$J$5:$J$304,"Easy") -> 8 | H7: =COUNTIFS('Use Case Catalog'!$C$5:$C$304,$B7,'Use Case Catalog'!$K$5:$K$304,"White Space") -> 10 | I7: =ROUND(AVERAGEIF('Use Case Catalog'!$C$5:$C$304,$B7,'Use Case Catalog'!$N$5:$N$304),1) -> 7.8
B8: Traffic & Road Safety | C8: =COUNTIF('Use Case Catalog'!$C$5:$C$304,$B8) -> 20 | D8: =COUNTIFS('Use Case Catalog'!$C$5:$C$304,$B8,'Use Case Catalog'!$H$5:$H$304,"External") -> 11 | E8: =COUNTIFS('Use Case Catalog'!$C$5:$C$304,$B8,'Use Case Catalog'!$H$5:$H$304,"Internal") -> 9 | F8: =COUNTIFS('Use Case Catalog'!$C$5:$C$304,$B8,'Use Case Catalog'!$I$5:$I$304,"High") -> 11 | G8: =COUNTIFS('Use Case Catalog'!$C$5:$C$304,$B8,'Use Case Catalog'!$J$5:$J$304,"Easy") -> 10 | H8: =COUNTIFS('Use Case Catalog'!$C$5:$C$304,$B8,'Use Case Catalog'!$K$5:$K$304,"White Space") -> 6 | I8: =ROUND(AVERAGEIF('Use Case Catalog'!$C$5:$C$304,$B8,'Use Case Catalog'!$N$5:$N$304),1) -> 8.2
B9: Cybercrime & Digital Fraud | C9: =COUNTIF('Use Case Catalog'!$C$5:$C$304,$B9) -> 20 | D9: =COUNTIFS('Use Case Catalog'!$C$5:$C$304,$B9,'Use Case Catalog'!$H$5:$H$304,"External") -> 13 | E9: =COUNTIFS('Use Case Catalog'!$C$5:$C$304,$B9,'Use Case Catalog'!$H$5:$H$304,"Internal") -> 7 | F9: =COUNTIFS('Use Case Catalog'!$C$5:$C$304,$B9,'Use Case Catalog'!$I$5:$I$304,"High") -> 13 | G9: =COUNTIFS('Use Case Catalog'!$C$5:$C$304,$B9,'Use Case Catalog'!$J$5:$J$304,"Easy") -> 10 | H9: =COUNTIFS('Use Case Catalog'!$C$5:$C$304,$B9,'Use Case Catalog'!$K$5:$K$304,"White Space") -> 8 | I9: =ROUND(AVERAGEIF('Use Case Catalog'!$C$5:$C$304,$B9,'Use Case Catalog'!$N$5:$N$304),1) -> 8.2
B10: Community Services & Smart Reports | C10: =COUNTIF('Use Case Catalog'!$C$5:$C$304,$B10) -> 20 | D10: =COUNTIFS('Use Case Catalog'!$C$5:$C$304,$B10,'Use Case Catalog'!$H$5:$H$304,"External") -> 19 | E10: =COUNTIFS('Use Case Catalog'!$C$5:$C$304,$B10,'Use Case Catalog'!$H$5:$H$304,"Internal") -> 1 | F10: =COUNTIFS('Use Case Catalog'!$C$5:$C$304,$B10,'Use Case Catalog'!$I$5:$I$304,"High") -> 6 | G10: =COUNTIFS('Use Case Catalog'!$C$5:$C$304,$B10,'Use Case Catalog'!$J$5:$J$304,"Easy") -> 17 | H10: =COUNTIFS('Use Case Catalog'!$C$5:$C$304,$B10,'Use Case Catalog'!$K$5:$K$304,"White Space") -> 2 | I10: =ROUND(AVERAGEIF('Use Case Catalog'!$C$5:$C$304,$B10,'Use Case Catalog'!$N$5:$N$304),1) -> 8.3
B11: Tourist Policing | C11: =COUNTIF('Use Case Catalog'!$C$5:$C$304,$B11) -> 20 | D11: =COUNTIFS('Use Case Catalog'!$C$5:$C$304,$B11,'Use Case Catalog'!$H$5:$H$304,"External") -> 20 | E11: =COUNTIFS('Use Case Catalog'!$C$5:$C$304,$B11,'Use Case Catalog'!$H$5:$H$304,"Internal") -> 0 | F11: =COUNTIFS('Use Case Catalog'!$C$5:$C$304,$B11,'Use Case Catalog'!$I$5:$I$304,"High") -> 7 | G11: =COUNTIFS('Use Case Catalog'!$C$5:$C$304,$B11,'Use Case Catalog'!$J$5:$J$304,"Easy") -> 11 | H11: =COUNTIFS('Use Case Catalog'!$C$5:$C$304,$B11,'Use Case Catalog'!$K$5:$K$304,"White Space") -> 10 | I11: =ROUND(AVERAGEIF('Use Case Catalog'!$C$5:$C$304,$B11,'Use Case Catalog'!$N$5:$N$304),1) -> 8
B12: Lost & Found & Property | C12: =COUNTIF('Use Case Catalog'!$C$5:$C$304,$B12) -> 20 | D12: =COUNTIFS('Use Case Catalog'!$C$5:$C$304,$B12,'Use Case Catalog'!$H$5:$H$304,"External") -> 17 | E12: =COUNTIFS('Use Case Catalog'!$C$5:$C$304,$B12,'Use Case Catalog'!$H$5:$H$304,"Internal") -> 3 | F12: =COUNTIFS('Use Case Catalog'!$C$5:$C$304,$B12,'Use Case Catalog'!$I$5:$I$304,"High") -> 6 | G12: =COUNTIFS('Use Case Catalog'!$C$5:$C$304,$B12,'Use Case Catalog'!$J$5:$J$304,"Easy") -> 14 | H12: =COUNTIFS('Use Case Catalog'!$C$5:$C$304,$B12,'Use Case Catalog'!$K$5:$K$304,"White Space") -> 10 | I12: =ROUND(AVERAGEIF('Use Case Catalog'!$C$5:$C$304,$B12,'Use Case Catalog'!$N$5:$N$304),1) -> 8
B13: Safe City & Surveillance (Oyoon) | C13: =COUNTIF('Use Case Catalog'!$C$5:$C$304,$B13) -> 20 | D13: =COUNTIFS('Use Case Catalog'!$C$5:$C$304,$B13,'Use Case Catalog'!$H$5:$H$304,"External") -> 4 | E13: =COUNTIFS('Use Case Catalog'!$C$5:$C$304,$B13,'Use Case Catalog'!$H$5:$H$304,"Internal") -> 16 | F13: =COUNTIFS('Use Case Catalog'!$C$5:$C$304,$B13,'Use Case Catalog'!$I$5:$I$304,"High") -> 11 | G13: =COUNTIFS('Use Case Catalog'!$C$5:$C$304,$B13,'Use Case Catalog'!$J$5:$J$304,"Easy") -> 5 | H13: =COUNTIFS('Use Case Catalog'!$C$5:$C$304,$B13,'Use Case Catalog'!$K$5:$K$304,"White Space") -> 7 | I13: =ROUND(AVERAGEIF('Use Case Catalog'!$C$5:$C$304,$B13,'Use Case Catalog'!$N$5:$N$304),1) -> 7.5
B14: Drugs, Weapons & Organized Crime | C14: =COUNTIF('Use Case Catalog'!$C$5:$C$304,$B14) -> 20 | D14: =COUNTIFS('Use Case Catalog'!$C$5:$C$304,$B14,'Use Case Catalog'!$H$5:$H$304,"External") -> 4 | E14: =COUNTIFS('Use Case Catalog'!$C$5:$C$304,$B14,'Use Case Catalog'!$H$5:$H$304,"Internal") -> 16 | F14: =COUNTIFS('Use Case Catalog'!$C$5:$C$304,$B14,'Use Case Catalog'!$I$5:$I$304,"High") -> 7 | G14: =COUNTIFS('Use Case Catalog'!$C$5:$C$304,$B14,'Use Case Catalog'!$J$5:$J$304,"Easy") -> 11 | H14: =COUNTIFS('Use Case Catalog'!$C$5:$C$304,$B14,'Use Case Catalog'!$K$5:$K$304,"White Space") -> 6 | I14: =ROUND(AVERAGEIF('Use Case Catalog'!$C$5:$C$304,$B14,'Use Case Catalog'!$N$5:$N$304),1) -> 7.3
B15: Family, Women & Children Protection | C15: =COUNTIF('Use Case Catalog'!$C$5:$C$304,$B15) -> 20 | D15: =COUNTIFS('Use Case Catalog'!$C$5:$C$304,$B15,'Use Case Catalog'!$H$5:$H$304,"External") -> 12 | E15: =COUNTIFS('Use Case Catalog'!$C$5:$C$304,$B15,'Use Case Catalog'!$H$5:$H$304,"Internal") -> 8 | F15: =COUNTIFS('Use Case Catalog'!$C$5:$C$304,$B15,'Use Case Catalog'!$I$5:$I$304,"High") -> 12 | G15: =COUNTIFS('Use Case Catalog'!$C$5:$C$304,$B15,'Use Case Catalog'!$J$5:$J$304,"Easy") -> 13 | H15: =COUNTIFS('Use Case Catalog'!$C$5:$C$304,$B15,'Use Case Catalog'!$K$5:$K$304,"White Space") -> 6 | I15: =ROUND(AVERAGEIF('Use Case Catalog'!$C$5:$C$304,$B15,'Use Case Catalog'!$N$5:$N$304),1) -> 8.1
B16: Corrections & Rehabilitation | C16: =COUNTIF('Use Case Catalog'!$C$5:$C$304,$B16) -> 20 | D16: =COUNTIFS('Use Case Catalog'!$C$5:$C$304,$B16,'Use Case Catalog'!$H$5:$H$304,"External") -> 6 | E16: =COUNTIFS('Use Case Catalog'!$C$5:$C$304,$B16,'Use Case Catalog'!$H$5:$H$304,"Internal") -> 14 | F16: =COUNTIFS('Use Case Catalog'!$C$5:$C$304,$B16,'Use Case Catalog'!$I$5:$I$304,"High") -> 9 | G16: =COUNTIFS('Use Case Catalog'!$C$5:$C$304,$B16,'Use Case Catalog'!$J$5:$J$304,"Easy") -> 10 | H16: =COUNTIFS('Use Case Catalog'!$C$5:$C$304,$B16,'Use Case Catalog'!$K$5:$K$304,"White Space") -> 4 | I16: =ROUND(AVERAGEIF('Use Case Catalog'!$C$5:$C$304,$B16,'Use Case Catalog'!$N$5:$N$304),1) -> 7.9
... B19: Intelligence, Prediction & Command (2040) | C19: =COUNTIF('Use Case Catalog'!$C$5:$C$304,$B19) -> 20 | D19: =COUNTIFS('Use Case Catalog'!$C$5:$C$304,$B19,'Use Case Catalog'!$H$5:$H$304,"External") -> 3 | E19: =COUNTIFS('Use Case Catalog'!$C$5:$C$304,$B19,'Use Case Catalog'!$H$5:$H$304,"Internal") -> 17 | F19: =COUNTIFS('Use Case Catalog'!$C$5:$C$304,$B19,'Use Case Catalog'!$I$5:$I$304,"High") -> 8 | G19: =COUNTIFS('Use Case Catalog'!$C$5:$C$304,$B19,'Use Case Catalog'!$J$5:$J$304,"Easy") -> 10 | H19: =COUNTIFS('Use Case Catalog'!$C$5:$C$304,$B19,'Use Case Catalog'!$K$5:$K$304,"White Space") -> 7 | I19: =ROUND(AVERAGEIF('Use Case Catalog'!$C$5:$C$304,$B19,'Use Case Catalog'!$N$5:$N$304),1) -> 7.6
B20: Total | C20: =SUM(C5:C19) -> 300 | D20: =SUM(D5:D19) -> 135 | E20: =SUM(E5:E19) -> 165 | F20: =SUM(F5:F19) -> 138 | G20: =SUM(G5:G19) -> 157 | H20: =SUM(H5:H19) -> 93 | I20: =ROUND(AVERAGE('Use Case Catalog'!$N$5:$N$304),1) -> 7.9
B22: Counts are live COUNTIF formulas over the catalog sheet; totals must equal 300. White Space column counts use cases with no comparable production system in Dubai.
